Classfile /Users/Matcha/Work/ideaWorkSpace/learnspace/Infrastructure/JavaCommon/target/classes/com/infrastructure/bridge/BaseContainer.class
  Last modified 2017年11月6日; size 1137 bytes
  MD5 checksum 642ebaa28a328e8f1a94dc979e8836a2
  Compiled from "BaseContainer.java"
public class com.infrastructure.bridge.BaseContainer<TYPE extends java.lang.Object> extends java.lang.Object implements com.infrastructure.bridge.IContainer<TYPE>
  minor version: 0
  major version: 53
  flags: (0x0021) ACC_PUBLIC, ACC_SUPER
  this_class: #3                          // com/infrastructure/bridge/BaseContainer
  super_class: #4                         // java/lang/Object
  interfaces: 1, fields: 1, methods: 4, attributes: 2
Constant pool:
   #1 = Methodref          #4.#31         // java/lang/Object."<init>":()V
   #2 = Fieldref           #3.#32         // com/infrastructure/bridge/BaseContainer.target:Ljava/lang/Object;
   #3 = Class              #33            // com/infrastructure/bridge/BaseContainer
   #4 = Class              #34            // java/lang/Object
   #5 = Class              #35            // com/infrastructure/bridge/IContainer
   #6 = Utf8               target
   #7 = Utf8               Ljava/lang/Object;
   #8 = Utf8               Signature
   #9 = Utf8               TTYPE;
  #10 = Utf8               <init>
  #11 = Utf8               ()V
  #12 = Utf8               Code
  #13 = Utf8               LineNumberTable
  #14 = Utf8               LocalVariableTable
  #15 = Utf8               this
  #16 = Utf8               Lcom/infrastructure/bridge/BaseContainer;
  #17 = Utf8               LocalVariableTypeTable
  #18 = Utf8               Lcom/infrastructure/bridge/BaseContainer<TTYPE;>;
  #19 = Utf8               (Ljava/lang/Object;)V
  #20 = Utf8               (TTYPE;)V
  #21 = Utf8               get
  #22 = Utf8               ()Ljava/lang/Object;
  #23 = Utf8               ()TTYPE;
  #24 = Utf8               set
  #25 = Utf8               (Ljava/lang/Object;)Ljava/lang/Object;
  #26 = Utf8               oldTarget
  #27 = Utf8               (TTYPE;)TTYPE;
  #28 = Utf8               <TYPE:Ljava/lang/Object;>Ljava/lang/Object;Lcom/infrastructure/bridge/IContainer<TTYPE;>;
  #29 = Utf8               SourceFile
  #30 = Utf8               BaseContainer.java
  #31 = NameAndType        #10:#11        // "<init>":()V
  #32 = NameAndType        #6:#7          // target:Ljava/lang/Object;
  #33 = Utf8               com/infrastructure/bridge/BaseContainer
  #34 = Utf8               java/lang/Object
  #35 = Utf8               com/infrastructure/bridge/IContainer
{
  protected TYPE target;
    descriptor: Ljava/lang/Object;
    flags: (0x0004) ACC_PROTECTED
    Signature: #9                           // TTYPE;

  public com.infrastructure.bridge.BaseContainer();
    descriptor: ()V
    flags: (0x0001) ACC_PUBLIC
    Code:
      stack=1, locals=1, args_size=1
         0: aload_0
         1: invokespecial #1                  // Method java/lang/Object."<init>":()V
         4: return
      LineNumberTable:
        line 8: 0
        line 9: 4
      LocalVariableTable:
        Start  Length  Slot  Name   Signature
            0       5     0  this   Lcom/infrastructure/bridge/BaseContainer;
      LocalVariableTypeTable:
        Start  Length  Slot  Name   Signature
            0       5     0  this   Lcom/infrastructure/bridge/BaseContainer<TTYPE;>;

  public com.infrastructure.bridge.BaseContainer(TYPE);
    descriptor: (Ljava/lang/Object;)V
    flags: (0x0001) ACC_PUBLIC
    Code:
      stack=2, locals=2, args_size=2
         0: aload_0
         1: invokespecial #1                  // Method java/lang/Object."<init>":()V
         4: aload_0
         5: aload_1
         6: putfield      #2                  // Field target:Ljava/lang/Object;
         9: return
      LineNumberTable:
        line 12: 0
        line 13: 4
        line 14: 9
      LocalVariableTable:
        Start  Length  Slot  Name   Signature
            0      10     0  this   Lcom/infrastructure/bridge/BaseContainer;
            0      10     1 target   Ljava/lang/Object;
      LocalVariableTypeTable:
        Start  Length  Slot  Name   Signature
            0      10     0  this   Lcom/infrastructure/bridge/BaseContainer<TTYPE;>;
            0      10     1 target   TTYPE;
    Signature: #20                          // (TTYPE;)V

  public TYPE get();
    descriptor: ()Ljava/lang/Object;
    flags: (0x0001) ACC_PUBLIC
    Code:
      stack=1, locals=1, args_size=1
         0: aload_0
         1: getfield      #2                  // Field target:Ljava/lang/Object;
         4: areturn
      LineNumberTable:
        line 19: 0
      LocalVariableTable:
        Start  Length  Slot  Name   Signature
            0       5     0  this   Lcom/infrastructure/bridge/BaseContainer;
      LocalVariableTypeTable:
        Start  Length  Slot  Name   Signature
            0       5     0  this   Lcom/infrastructure/bridge/BaseContainer<TTYPE;>;
    Signature: #23                          // ()TTYPE;

  public TYPE set(TYPE);
    descriptor: (Ljava/lang/Object;)Ljava/lang/Object;
    flags: (0x0001) ACC_PUBLIC
    Code:
      stack=2, locals=3, args_size=2
         0: aload_0
         1: getfield      #2                  // Field target:Ljava/lang/Object;
         4: astore_2
         5: aload_0
         6: aload_1
         7: putfield      #2                  // Field target:Ljava/lang/Object;
        10: aload_2
        11: areturn
      LineNumberTable:
        line 25: 0
        line 26: 5
        line 27: 10
      LocalVariableTable:
        Start  Length  Slot  Name   Signature
            0      12     0  this   Lcom/infrastructure/bridge/BaseContainer;
            0      12     1 target   Ljava/lang/Object;
            5       7     2 oldTarget   Ljava/lang/Object;
      LocalVariableTypeTable:
        Start  Length  Slot  Name   Signature
            0      12     0  this   Lcom/infrastructure/bridge/BaseContainer<TTYPE;>;
            0      12     1 target   TTYPE;
            5       7     2 oldTarget   TTYPE;
    Signature: #27                          // (TTYPE;)TTYPE;
}
Signature: #28                          // <TYPE:Ljava/lang/Object;>Ljava/lang/Object;Lcom/infrastructure/bridge/IContainer<TTYPE;>;
SourceFile: "BaseContainer.java"
