Classfile /Users/Matcha/Work/ideaWorkSpace/learnspace/Infrastructure/JavaCommon/target/classes/com/infrastructure/bridge/LockContainer.class
  Last modified 2017年11月6日; size 1681 bytes
  MD5 checksum e6d9db8d1710fb8f6cddf9af82f22185
  Compiled from "LockContainer.java"
public class com.infrastructure.bridge.LockContainer<TYPE extends java.lang.Object> extends com.infrastructure.bridge.BaseContainer<TYPE>
  minor version: 0
  major version: 53
  flags: (0x0021) ACC_PUBLIC, ACC_SUPER
  this_class: #14                         // com/infrastructure/bridge/LockContainer
  super_class: #15                        // com/infrastructure/bridge/BaseContainer
  interfaces: 0, fields: 3, methods: 4, attributes: 2
Constant pool:
   #1 = Methodref          #14.#47        // com/infrastructure/bridge/LockContainer."<init>":(Ljava/lang/Object;)V
   #2 = Methodref          #15.#47        // com/infrastructure/bridge/BaseContainer."<init>":(Ljava/lang/Object;)V
   #3 = Class              #48            // java/util/concurrent/locks/ReentrantReadWriteLock
   #4 = Methodref          #3.#49         // java/util/concurrent/locks/ReentrantReadWriteLock."<init>":(Z)V
   #5 = Fieldref           #14.#50        // com/infrastructure/bridge/LockContainer.lock:Ljava/util/concurrent/locks/ReadWriteLock;
   #6 = InterfaceMethodref #51.#52        // java/util/concurrent/locks/ReadWriteLock.readLock:()Ljava/util/concurrent/locks/Lock;
   #7 = Fieldref           #14.#53        // com/infrastructure/bridge/LockContainer.readLock:Ljava/util/concurrent/locks/Lock;
   #8 = InterfaceMethodref #51.#54        // java/util/concurrent/locks/ReadWriteLock.writeLock:()Ljava/util/concurrent/locks/Lock;
   #9 = Fieldref           #14.#55        // com/infrastructure/bridge/LockContainer.writeLock:Ljava/util/concurrent/locks/Lock;
  #10 = InterfaceMethodref #56.#57        // java/util/concurrent/locks/Lock.lock:()V
  #11 = Methodref          #15.#58        // com/infrastructure/bridge/BaseContainer.get:()Ljava/lang/Object;
  #12 = InterfaceMethodref #56.#59        // java/util/concurrent/locks/Lock.unlock:()V
  #13 = Methodref          #15.#60        // com/infrastructure/bridge/BaseContainer.set:(Ljava/lang/Object;)Ljava/lang/Object;
  #14 = Class              #61            // com/infrastructure/bridge/LockContainer
  #15 = Class              #62            // com/infrastructure/bridge/BaseContainer
  #16 = Utf8               lock
  #17 = Utf8               Ljava/util/concurrent/locks/ReadWriteLock;
  #18 = Utf8               readLock
  #19 = Utf8               Ljava/util/concurrent/locks/Lock;
  #20 = Utf8               writeLock
  #21 = Utf8               <init>
  #22 = Utf8               ()V
  #23 = Utf8               Code
  #24 = Utf8               LineNumberTable
  #25 = Utf8               LocalVariableTable
  #26 = Utf8               this
  #27 = Utf8               Lcom/infrastructure/bridge/LockContainer;
  #28 = Utf8               LocalVariableTypeTable
  #29 = Utf8               Lcom/infrastructure/bridge/LockContainer<TTYPE;>;
  #30 = Utf8               (Ljava/lang/Object;)V
  #31 = Utf8               target
  #32 = Utf8               Ljava/lang/Object;
  #33 = Utf8               TTYPE;
  #34 = Utf8               Signature
  #35 = Utf8               (TTYPE;)V
  #36 = Utf8               get
  #37 = Utf8               ()Ljava/lang/Object;
  #38 = Utf8               StackMapTable
  #39 = Class              #63            // java/lang/Throwable
  #40 = Utf8               ()TTYPE;
  #41 = Utf8               set
  #42 = Utf8               (Ljava/lang/Object;)Ljava/lang/Object;
  #43 = Utf8               (TTYPE;)TTYPE;
  #44 = Utf8               <TYPE:Ljava/lang/Object;>Lcom/infrastructure/bridge/BaseContainer<TTYPE;>;
  #45 = Utf8               SourceFile
  #46 = Utf8               LockContainer.java
  #47 = NameAndType        #21:#30        // "<init>":(Ljava/lang/Object;)V
  #48 = Utf8               java/util/concurrent/locks/ReentrantReadWriteLock
  #49 = NameAndType        #21:#64        // "<init>":(Z)V
  #50 = NameAndType        #16:#17        // lock:Ljava/util/concurrent/locks/ReadWriteLock;
  #51 = Class              #65            // java/util/concurrent/locks/ReadWriteLock
  #52 = NameAndType        #18:#66        // readLock:()Ljava/util/concurrent/locks/Lock;
  #53 = NameAndType        #18:#19        // readLock:Ljava/util/concurrent/locks/Lock;
  #54 = NameAndType        #20:#66        // writeLock:()Ljava/util/concurrent/locks/Lock;
  #55 = NameAndType        #20:#19        // writeLock:Ljava/util/concurrent/locks/Lock;
  #56 = Class              #67            // java/util/concurrent/locks/Lock
  #57 = NameAndType        #16:#22        // lock:()V
  #58 = NameAndType        #36:#37        // get:()Ljava/lang/Object;
  #59 = NameAndType        #68:#22        // unlock:()V
  #60 = NameAndType        #41:#42        // set:(Ljava/lang/Object;)Ljava/lang/Object;
  #61 = Utf8               com/infrastructure/bridge/LockContainer
  #62 = Utf8               com/infrastructure/bridge/BaseContainer
  #63 = Utf8               java/lang/Throwable
  #64 = Utf8               (Z)V
  #65 = Utf8               java/util/concurrent/locks/ReadWriteLock
  #66 = Utf8               ()Ljava/util/concurrent/locks/Lock;
  #67 = Utf8               java/util/concurrent/locks/Lock
  #68 = Utf8               unlock
{
  private java.util.concurrent.locks.ReadWriteLock lock;
    descriptor: Ljava/util/concurrent/locks/ReadWriteLock;
    flags: (0x0002) ACC_PRIVATE

  private java.util.concurrent.locks.Lock readLock;
    descriptor: Ljava/util/concurrent/locks/Lock;
    flags: (0x0002) ACC_PRIVATE

  private java.util.concurrent.locks.Lock writeLock;
    descriptor: Ljava/util/concurrent/locks/Lock;
    flags: (0x0002) ACC_PRIVATE

  public com.infrastructure.bridge.LockContainer();
    descriptor: ()V
    flags: (0x0001) ACC_PUBLIC
    Code:
      stack=2, locals=1, args_size=1
         0: aload_0
         1: aconst_null
         2: invokespecial #1                  // Method "<init>":(Ljava/lang/Object;)V
         5: return
      LineNumberTable:
        line 15: 0
        line 16: 5
      LocalVariableTable:
        Start  Length  Slot  Name   Signature
            0       6     0  this   Lcom/infrastructure/bridge/LockContainer;
      LocalVariableTypeTable:
        Start  Length  Slot  Name   Signature
            0       6     0  this   Lcom/infrastructure/bridge/LockContainer<TTYPE;>;

  public com.infrastructure.bridge.LockContainer(TYPE);
    descriptor: (Ljava/lang/Object;)V
    flags: (0x0001) ACC_PUBLIC
    Code:
      stack=4, locals=2, args_size=2
         0: aload_0
         1: aload_1
         2: invokespecial #2                  // Method com/infrastructure/bridge/BaseContainer."<init>":(Ljava/lang/Object;)V
         5: aload_0
         6: new           #3                  // class java/util/concurrent/locks/ReentrantReadWriteLock
         9: dup
        10: iconst_0
        11: invokespecial #4                  // Method java/util/concurrent/locks/ReentrantReadWriteLock."<init>":(Z)V
        14: putfield      #5                  // Field lock:Ljava/util/concurrent/locks/ReadWriteLock;
        17: aload_0
        18: aload_0
        19: getfield      #5                  // Field lock:Ljava/util/concurrent/locks/ReadWriteLock;
        22: invokeinterface #6,  1            // InterfaceMethod java/util/concurrent/locks/ReadWriteLock.readLock:()Ljava/util/concurrent/locks/Lock;
        27: putfield      #7                  // Field readLock:Ljava/util/concurrent/locks/Lock;
        30: aload_0
        31: aload_0
        32: getfield      #5                  // Field lock:Ljava/util/concurrent/locks/ReadWriteLock;
        35: invokeinterface #8,  1            // InterfaceMethod java/util/concurrent/locks/ReadWriteLock.writeLock:()Ljava/util/concurrent/locks/Lock;
        40: putfield      #9                  // Field writeLock:Ljava/util/concurrent/locks/Lock;
        43: return
      LineNumberTable:
        line 20: 0
        line 21: 5
        line 22: 17
        line 23: 30
        line 24: 43
      LocalVariableTable:
        Start  Length  Slot  Name   Signature
            0      44     0  this   Lcom/infrastructure/bridge/LockContainer;
            0      44     1 target   Ljava/lang/Object;
      LocalVariableTypeTable:
        Start  Length  Slot  Name   Signature
            0      44     0  this   Lcom/infrastructure/bridge/LockContainer<TTYPE;>;
            0      44     1 target   TTYPE;
    Signature: #35                          // (TTYPE;)V

  public TYPE get();
    descriptor: ()Ljava/lang/Object;
    flags: (0x0001) ACC_PUBLIC
    Code:
      stack=1, locals=3, args_size=1
         0: aload_0
         1: getfield      #7                  // Field readLock:Ljava/util/concurrent/locks/Lock;
         4: invokeinterface #10,  1           // InterfaceMethod java/util/concurrent/locks/Lock.lock:()V
         9: aload_0
        10: invokespecial #11                 // Method com/infrastructure/bridge/BaseContainer.get:()Ljava/lang/Object;
        13: astore_1
        14: aload_0
        15: getfield      #7                  // Field readLock:Ljava/util/concurrent/locks/Lock;
        18: invokeinterface #12,  1           // InterfaceMethod java/util/concurrent/locks/Lock.unlock:()V
        23: aload_1
        24: areturn
        25: astore_2
        26: aload_0
        27: getfield      #7                  // Field readLock:Ljava/util/concurrent/locks/Lock;
        30: invokeinterface #12,  1           // InterfaceMethod java/util/concurrent/locks/Lock.unlock:()V
        35: aload_2
        36: athrow
      Exception table:
         from    to  target type
             9    14    25   any
      LineNumberTable:
        line 29: 0
        line 32: 9
        line 36: 14
        line 32: 23
        line 36: 25
      LocalVariableTable:
        Start  Length  Slot  Name   Signature
            0      37     0  this   Lcom/infrastructure/bridge/LockContainer;
      LocalVariableTypeTable:
        Start  Length  Slot  Name   Signature
            0      37     0  this   Lcom/infrastructure/bridge/LockContainer<TTYPE;>;
      StackMapTable: number_of_entries = 1
        frame_type = 89 /* same_locals_1_stack_item */
          stack = [ class java/lang/Throwable ]
    Signature: #40                          // ()TTYPE;

  public TYPE set(TYPE);
    descriptor: (Ljava/lang/Object;)Ljava/lang/Object;
    flags: (0x0001) ACC_PUBLIC
    Code:
      stack=2, locals=4, args_size=2
         0: aload_0
         1: getfield      #9                  // Field writeLock:Ljava/util/concurrent/locks/Lock;
         4: invokeinterface #10,  1           // InterfaceMethod java/util/concurrent/locks/Lock.lock:()V
         9: aload_0
        10: aload_1
        11: invokespecial #13                 // Method com/infrastructure/bridge/BaseContainer.set:(Ljava/lang/Object;)Ljava/lang/Object;
        14: astore_2
        15: aload_0
        16: getfield      #9                  // Field writeLock:Ljava/util/concurrent/locks/Lock;
        19: invokeinterface #12,  1           // InterfaceMethod java/util/concurrent/locks/Lock.unlock:()V
        24: aload_2
        25: areturn
        26: astore_3
        27: aload_0
        28: getfield      #9                  // Field writeLock:Ljava/util/concurrent/locks/Lock;
        31: invokeinterface #12,  1           // InterfaceMethod java/util/concurrent/locks/Lock.unlock:()V
        36: aload_3
        37: athrow
      Exception table:
         from    to  target type
             9    15    26   any
      LineNumberTable:
        line 43: 0
        line 46: 9
        line 50: 15
        line 46: 24
        line 50: 26
      LocalVariableTable:
        Start  Length  Slot  Name   Signature
            0      38     0  this   Lcom/infrastructure/bridge/LockContainer;
            0      38     1 target   Ljava/lang/Object;
      LocalVariableTypeTable:
        Start  Length  Slot  Name   Signature
            0      38     0  this   Lcom/infrastructure/bridge/LockContainer<TTYPE;>;
            0      38     1 target   TTYPE;
      StackMapTable: number_of_entries = 1
        frame_type = 90 /* same_locals_1_stack_item */
          stack = [ class java/lang/Throwable ]
    Signature: #43                          // (TTYPE;)TTYPE;
}
Signature: #44                          // <TYPE:Ljava/lang/Object;>Lcom/infrastructure/bridge/BaseContainer<TTYPE;>;
SourceFile: "LockContainer.java"
