Classfile /Users/Matcha/Work/ideaWorkSpace/learnspace/Infrastructure/JavaCommon/target/classes/com/infrastructure/bridge/StringLockContainer.class
  Last modified 2017年11月6日; size 441 bytes
  MD5 checksum 0abf31df4d98f572589440c61a748bff
  Compiled from "StringLockContainer.java"
public class com.infrastructure.bridge.StringLockContainer extends com.infrastructure.bridge.LockContainer<java.lang.String>
  minor version: 0
  major version: 53
  flags: (0x0021) ACC_PUBLIC, ACC_SUPER
  this_class: #2                          // com/infrastructure/bridge/StringLockContainer
  super_class: #3                         // com/infrastructure/bridge/LockContainer
  interfaces: 0, fields: 0, methods: 1, attributes: 2
Constant pool:
   #1 = Methodref          #3.#15         // com/infrastructure/bridge/LockContainer."<init>":()V
   #2 = Class              #16            // com/infrastructure/bridge/StringLockContainer
   #3 = Class              #17            // com/infrastructure/bridge/LockContainer
   #4 = Utf8               <init>
   #5 = Utf8               ()V
   #6 = Utf8               Code
   #7 = Utf8               LineNumberTable
   #8 = Utf8               LocalVariableTable
   #9 = Utf8               this
  #10 = Utf8               Lcom/infrastructure/bridge/StringLockContainer;
  #11 = Utf8               Signature
  #12 = Utf8               Lcom/infrastructure/bridge/LockContainer<Ljava/lang/String;>;
  #13 = Utf8               SourceFile
  #14 = Utf8               StringLockContainer.java
  #15 = NameAndType        #4:#5          // "<init>":()V
  #16 = Utf8               com/infrastructure/bridge/StringLockContainer
  #17 = Utf8               com/infrastructure/bridge/LockContainer
{
  public com.infrastructure.bridge.StringLockContainer();
    descriptor: ()V
    flags: (0x0001) ACC_PUBLIC
    Code:
      stack=1, locals=1, args_size=1
         0: aload_0
         1: invokespecial #1                  // Method com/infrastructure/bridge/LockContainer."<init>":()V
         4: return
      LineNumberTable:
        line 3: 0
      LocalVariableTable:
        Start  Length  Slot  Name   Signature
            0       5     0  this   Lcom/infrastructure/bridge/StringLockContainer;
}
Signature: #12                          // Lcom/infrastructure/bridge/LockContainer<Ljava/lang/String;>;
SourceFile: "StringLockContainer.java"
