Classfile /Users/Matcha/Work/ideaWorkSpace/learnspace/Infrastructure/JavaCommon/target/classes/com/infrastructure/bridge/StringContainer.class
  Last modified 2017年11月6日; size 1625 bytes
  MD5 checksum d097f3c455078aba6f07c0067ba1f779
  Compiled from "StringContainer.java"
public class com.infrastructure.bridge.StringContainer extends java.lang.Object implements com.infrastructure.bridge.IContainer<java.lang.String>
  minor version: 0
  major version: 53
  flags: (0x0021) ACC_PUBLIC, ACC_SUPER
  this_class: #12                         // com/infrastructure/bridge/StringContainer
  super_class: #13                        // java/lang/Object
  interfaces: 1, fields: 1, methods: 6, attributes: 2
Constant pool:
   #1 = Methodref          #12.#45        // com/infrastructure/bridge/StringContainer."<init>":(Ljava/lang/String;)V
   #2 = Methodref          #13.#46        // java/lang/Object."<init>":()V
   #3 = Class              #47            // java/util/concurrent/atomic/AtomicStampedReference
   #4 = Methodref          #3.#48         // java/util/concurrent/atomic/AtomicStampedReference."<init>":(Ljava/lang/Object;I)V
   #5 = Fieldref           #12.#49        // com/infrastructure/bridge/StringContainer.targetReference:Ljava/util/concurrent/atomic/AtomicStampedReference;
   #6 = Methodref          #3.#50         // java/util/concurrent/atomic/AtomicStampedReference.getReference:()Ljava/lang/Object;
   #7 = Class              #51            // java/lang/String
   #8 = Methodref          #3.#52         // java/util/concurrent/atomic/AtomicStampedReference.get:([I)Ljava/lang/Object;
   #9 = Methodref          #3.#53         // java/util/concurrent/atomic/AtomicStampedReference.compareAndSet:(Ljava/lang/Object;Ljava/lang/Object;II)Z
  #10 = Methodref          #12.#54        // com/infrastructure/bridge/StringContainer.set:(Ljava/lang/String;)Ljava/lang/String;
  #11 = Methodref          #12.#55        // com/infrastructure/bridge/StringContainer.get:()Ljava/lang/String;
  #12 = Class              #56            // com/infrastructure/bridge/StringContainer
  #13 = Class              #57            // java/lang/Object
  #14 = Class              #58            // com/infrastructure/bridge/IContainer
  #15 = Utf8               targetReference
  #16 = Utf8               Ljava/util/concurrent/atomic/AtomicStampedReference;
  #17 = Utf8               Signature
  #18 = Utf8               Ljava/util/concurrent/atomic/AtomicStampedReference<Ljava/lang/String;>;
  #19 = Utf8               <init>
  #20 = Utf8               ()V
  #21 = Utf8               Code
  #22 = Utf8               LineNumberTable
  #23 = Utf8               LocalVariableTable
  #24 = Utf8               this
  #25 = Utf8               Lcom/infrastructure/bridge/StringContainer;
  #26 = Utf8               (Ljava/lang/String;)V
  #27 = Utf8               target
  #28 = Utf8               Ljava/lang/String;
  #29 = Utf8               get
  #30 = Utf8               ()Ljava/lang/String;
  #31 = Utf8               set
  #32 = Utf8               (Ljava/lang/String;)Ljava/lang/String;
  #33 = Utf8               stampHolder
  #34 = Utf8               [I
  #35 = Utf8               oldTarget
  #36 = Utf8               stamp
  #37 = Utf8               I
  #38 = Utf8               StackMapTable
  #39 = Class              #34            // "[I"
  #40 = Utf8               (Ljava/lang/Object;)Ljava/lang/Object;
  #41 = Utf8               ()Ljava/lang/Object;
  #42 = Utf8               Ljava/lang/Object;Lcom/infrastructure/bridge/IContainer<Ljava/lang/String;>;
  #43 = Utf8               SourceFile
  #44 = Utf8               StringContainer.java
  #45 = NameAndType        #19:#26        // "<init>":(Ljava/lang/String;)V
  #46 = NameAndType        #19:#20        // "<init>":()V
  #47 = Utf8               java/util/concurrent/atomic/AtomicStampedReference
  #48 = NameAndType        #19:#59        // "<init>":(Ljava/lang/Object;I)V
  #49 = NameAndType        #15:#16        // targetReference:Ljava/util/concurrent/atomic/AtomicStampedReference;
  #50 = NameAndType        #60:#41        // getReference:()Ljava/lang/Object;
  #51 = Utf8               java/lang/String
  #52 = NameAndType        #29:#61        // get:([I)Ljava/lang/Object;
  #53 = NameAndType        #62:#63        // compareAndSet:(Ljava/lang/Object;Ljava/lang/Object;II)Z
  #54 = NameAndType        #31:#32        // set:(Ljava/lang/String;)Ljava/lang/String;
  #55 = NameAndType        #29:#30        // get:()Ljava/lang/String;
  #56 = Utf8               com/infrastructure/bridge/StringContainer
  #57 = Utf8               java/lang/Object
  #58 = Utf8               com/infrastructure/bridge/IContainer
  #59 = Utf8               (Ljava/lang/Object;I)V
  #60 = Utf8               getReference
  #61 = Utf8               ([I)Ljava/lang/Object;
  #62 = Utf8               compareAndSet
  #63 = Utf8               (Ljava/lang/Object;Ljava/lang/Object;II)Z
{
  private java.util.concurrent.atomic.AtomicStampedReference<java.lang.String> targetReference;
    descriptor: Ljava/util/concurrent/atomic/AtomicStampedReference;
    flags: (0x0002) ACC_PRIVATE
    Signature: #18                          // Ljava/util/concurrent/atomic/AtomicStampedReference<Ljava/lang/String;>;

  public com.infrastructure.bridge.StringContainer();
    descriptor: ()V
    flags: (0x0001) ACC_PUBLIC
    Code:
      stack=2, locals=1, args_size=1
         0: aload_0
         1: aconst_null
         2: invokespecial #1                  // Method "<init>":(Ljava/lang/String;)V
         5: return
      LineNumberTable:
        line 11: 0
        line 12: 5
      LocalVariableTable:
        Start  Length  Slot  Name   Signature
            0       6     0  this   Lcom/infrastructure/bridge/StringContainer;

  public com.infrastructure.bridge.StringContainer(java.lang.String);
    descriptor: (Ljava/lang/String;)V
    flags: (0x0001) ACC_PUBLIC
    Code:
      stack=5, locals=2, args_size=2
         0: aload_0
         1: invokespecial #2                  // Method java/lang/Object."<init>":()V
         4: aload_0
         5: new           #3                  // class java/util/concurrent/atomic/AtomicStampedReference
         8: dup
         9: aload_1
        10: iconst_0
        11: invokespecial #4                  // Method java/util/concurrent/atomic/AtomicStampedReference."<init>":(Ljava/lang/Object;I)V
        14: putfield      #5                  // Field targetReference:Ljava/util/concurrent/atomic/AtomicStampedReference;
        17: return
      LineNumberTable:
        line 15: 0
        line 16: 4
        line 17: 17
      LocalVariableTable:
        Start  Length  Slot  Name   Signature
            0      18     0  this   Lcom/infrastructure/bridge/StringContainer;
            0      18     1 target   Ljava/lang/String;

  public java.lang.String get();
    descriptor: ()Ljava/lang/String;
    flags: (0x0001) ACC_PUBLIC
    Code:
      stack=1, locals=1, args_size=1
         0: aload_0
         1: getfield      #5                  // Field targetReference:Ljava/util/concurrent/atomic/AtomicStampedReference;
         4: invokevirtual #6                  // Method java/util/concurrent/atomic/AtomicStampedReference.getReference:()Ljava/lang/Object;
         7: checkcast     #7                  // class java/lang/String
        10: areturn
      LineNumberTable:
        line 22: 0
      LocalVariableTable:
        Start  Length  Slot  Name   Signature
            0      11     0  this   Lcom/infrastructure/bridge/StringContainer;

  public java.lang.String set(java.lang.String);
    descriptor: (Ljava/lang/String;)Ljava/lang/String;
    flags: (0x0001) ACC_PUBLIC
    Code:
      stack=6, locals=5, args_size=2
         0: iconst_1
         1: newarray       int
         3: astore_2
         4: aload_0
         5: getfield      #5                  // Field targetReference:Ljava/util/concurrent/atomic/AtomicStampedReference;
         8: aload_2
         9: invokevirtual #8                  // Method java/util/concurrent/atomic/AtomicStampedReference.get:([I)Ljava/lang/Object;
        12: checkcast     #7                  // class java/lang/String
        15: astore_3
        16: aload_2
        17: iconst_0
        18: iaload
        19: istore        4
        21: aload_0
        22: getfield      #5                  // Field targetReference:Ljava/util/concurrent/atomic/AtomicStampedReference;
        25: aload_3
        26: aload_1
        27: iload         4
        29: iload         4
        31: iconst_1
        32: iadd
        33: invokevirtual #9                  // Method java/util/concurrent/atomic/AtomicStampedReference.compareAndSet:(Ljava/lang/Object;Ljava/lang/Object;II)Z
        36: ifeq          4
        39: aload_3
        40: areturn
      LineNumberTable:
        line 28: 0
        line 33: 4
        line 34: 16
        line 35: 21
        line 36: 39
      LocalVariableTable:
        Start  Length  Slot  Name   Signature
            0      41     0  this   Lcom/infrastructure/bridge/StringContainer;
            0      41     1 target   Ljava/lang/String;
            4      37     2 stampHolder   [I
           16      25     3 oldTarget   Ljava/lang/String;
           21      20     4 stamp   I
      StackMapTable: number_of_entries = 1
        frame_type = 252 /* append */
          offset_delta = 4
          locals = [ class "[I" ]

  public java.lang.Object set(java.lang.Object);
    descriptor: (Ljava/lang/Object;)Ljava/lang/Object;
    flags: (0x1041) ACC_PUBLIC, ACC_BRIDGE, ACC_SYNTHETIC
    Code:
      stack=2, locals=2, args_size=2
         0: aload_0
         1: aload_1
         2: checkcast     #7                  // class java/lang/String
         5: invokevirtual #10                 // Method set:(Ljava/lang/String;)Ljava/lang/String;
         8: areturn
      LineNumberTable:
        line 5: 0
      LocalVariableTable:
        Start  Length  Slot  Name   Signature
            0       9     0  this   Lcom/infrastructure/bridge/StringContainer;

  public java.lang.Object get();
    descriptor: ()Ljava/lang/Object;
    flags: (0x1041) ACC_PUBLIC, ACC_BRIDGE, ACC_SYNTHETIC
    Code:
      stack=1, locals=1, args_size=1
         0: aload_0
         1: invokevirtual #11                 // Method get:()Ljava/lang/String;
         4: areturn
      LineNumberTable:
        line 5: 0
      LocalVariableTable:
        Start  Length  Slot  Name   Signature
            0       5     0  this   Lcom/infrastructure/bridge/StringContainer;
}
Signature: #42                          // Ljava/lang/Object;Lcom/infrastructure/bridge/IContainer<Ljava/lang/String;>;
SourceFile: "StringContainer.java"
